{
  "HALProvider": {
    "Other Devices": {
      "Victor SPX[1]": {
        "header": {
          "open": true
        }
      },
      "Victor SPX[2]": {
        "header": {
          "open": true
        }
      },
      "Victor SPX[3]": {
        "header": {
          "open": true
        }
      },
      "Victor SPX[4]": {
        "header": {
          "open": true
        }
      }
    },
    "PWM Outputs": {
      "window": {
        "visible": true
      }
    }
  },
  "NTProvider": {
    "types": {
      "/FMSInfo": "FMSInfo"
    }
  }
}
